cognite/replicator/__init__.py
cognite/replicator/__main__.py
cognite/replicator/_version.py
cognite/replicator/assets.py
cognite/replicator/datapoints.py
cognite/replicator/datasets.py
cognite/replicator/events.py
cognite/replicator/files.py
cognite/replicator/raw.py
cognite/replicator/relationships.py
cognite/replicator/replication.py
cognite/replicator/sequence_rows.py
cognite/replicator/sequences.py
cognite/replicator/time_series.py
cognite_replicator-1.3.2.dist-info/LICENSE
cognite_replicator-1.3.2.dist-info/METADATA
cognite_replicator-1.3.2.dist-info/WHEEL
cognite_replicator-1.3.2.dist-info/entry_points.txt
cognite_replicator-1.3.2.dist-info/RECORD
