Metadata-Version: 2.1
Name: cognite_replicator
Version: 1.3.2
Summary: Python package for replicating data across CDF projects. Copyright 2023 Cognite AS
License: Apache-2.0
Author: Even Wiik Thomassen
Author-email: even.thomassen@cognite.com
Requires-Python: >=3.11,<4.0
Classifier: Development Status :: 4 - Beta
Classifier: Intended Audience :: Developers
Classifier: Intended Audience :: System Administrators
Classifier: License :: OSI Approved :: Apache Software License
Classifier: Natural Language :: English
Classifier: Programming Language :: Python :: 3
Classifier: Programming Language :: Python :: 3.11
Classifier: Programming Language :: Python :: 3.12
Requires-Dist: cognite-sdk (>=7.13.8,<8.0.0)
Requires-Dist: google-cloud-logging (>=1.12,<2.0)
Requires-Dist: protobuf (>=4.0.0,<5.0.0)
Requires-Dist: pyyaml (>=6.0.1,<7.0.0)
